emailall/__init__.py
emailall/common/__init__.py
emailall/common/output.py
emailall/common/search.py
emailall/common/utils.py
emailall/config/__init__.py
emailall/config/api.py
emailall/config/log.py
emailall/config/setting.py
emailall/lib.py
emailall/modules/__init__.py
emailall/modules/collect.py
emailall/modules/datasets/Emailf.py
emailall/modules/datasets/phonebook.py
emailall/modules/datasets/skymem.py
emailall/modules/datasets/snov.py
emailall/modules/datasets/veryvp.py
emailall/modules/module.py
emailall/modules/search/ask.py
emailall/modules/search/baidu.py
emailall/modules/search/bingcn.py
emailall/modules/search/githubapi.py
emailall/modules/search/google.py
emailall/modules/search/qwant.py
emailall/modules/search/so.py
emailall/modules/search/sogou.py
emailall-0.1.0.dist-info/WHEEL
emailall-0.1.0.dist-info/METADATA
emailall-0.1.0.dist-info/RECORD
