Metadata-Version: 2.1
Name: emailall
Version: 0.1.0
Summary: EmailAll is a powerful Email Collect tool —— 一款强大的邮箱收集工具
Author: zmf963
Author-email: zmf96@qq.com
Requires-Python: >=3.8,<4.0
Classifier: Programming Language :: Python :: 3
Classifier: Programming Language :: Python :: 3.10
Classifier: Programming Language :: Python :: 3.8
Classifier: Programming Language :: Python :: 3.9
Requires-Dist: fake-useragent (>=0.1.11,<0.2.0)
Requires-Dist: fire (>=0.4.0,<0.5.0)
Requires-Dist: loguru (>=0.6.0,<0.7.0)
Requires-Dist: lxml (>=4.8.0,<5.0.0)
Requires-Dist: prettytable (>=3.1.1,<4.0.0)
Requires-Dist: requests (>=2.27.1,<3.0.0)
Requires-Dist: urllib3 (>=1.26.8,<2.0.0)
